odoo/addons/crm_sale_marketing/README.rst
odoo/addons/crm_sale_marketing/__init__.py
odoo/addons/crm_sale_marketing/__manifest__.py
odoo/addons/crm_sale_marketing/i18n/crm_sale_marketing.pot
odoo/addons/crm_sale_marketing/i18n/de.po
odoo/addons/crm_sale_marketing/i18n/eu_ES.po
odoo/addons/crm_sale_marketing/i18n/it.po
odoo/addons/crm_sale_marketing/i18n/tr.po
odoo/addons/crm_sale_marketing/readme/CONFIGURE.rst
odoo/addons/crm_sale_marketing/readme/CONTRIBUTORS.rst
odoo/addons/crm_sale_marketing/readme/DESCRIPTION.rst
odoo/addons/crm_sale_marketing/readme/INSTALL.rst
odoo/addons/crm_sale_marketing/readme/USAGE.rst
odoo/addons/crm_sale_marketing/static/description/icon.png
odoo/addons/crm_sale_marketing/static/description/index.html
odoo/addons/crm_sale_marketing/views/crm_sale_marketing.xml
odoo12_addon_crm_sale_marketing-12.0.1.0.0.99.dev8.dist-info/METADATA
odoo12_addon_crm_sale_marketing-12.0.1.0.0.99.dev8.dist-info/WHEEL
odoo12_addon_crm_sale_marketing-12.0.1.0.0.99.dev8.dist-info/top_level.txt
odoo12_addon_crm_sale_marketing-12.0.1.0.0.99.dev8.dist-info/RECORD
